bin/__init__.py
bin/geo2topo.py
bin/topo2geo.py
bin/topoquantize.py
pytopojson/__init__.py
pytopojson/bbox.py
pytopojson/bisect.py
pytopojson/bounds.py
pytopojson/commons.py
pytopojson/cut.py
pytopojson/dedup.py
pytopojson/delta.py
pytopojson/extract.py
pytopojson/feature.py
pytopojson/geometry.py
pytopojson/identity.py
pytopojson/join.py
pytopojson/merge.py
pytopojson/mesh.py
pytopojson/neighbors.py
pytopojson/prequantize.py
pytopojson/quantize.py
pytopojson/stitch.py
pytopojson/topology.py
pytopojson/transform.py
pytopojson/untransform.py
pytopojson/hash/__init__.py
pytopojson/hash/hash.py
pytopojson/hash/point.py
pytopojson-1.1.2.data/scripts/geo2topo.py
pytopojson-1.1.2.data/scripts/topo2geo.py
pytopojson-1.1.2.data/scripts/topoquantize.py
tests/__init__.py
tests/in_delta.py
tests/test_bbox.py
tests/test_bounds.py
tests/test_cut.py
tests/test_dedup.py
tests/test_delta.py
tests/test_extract.py
tests/test_feature.py
tests/test_geo2topo.py
tests/test_geometry.py
tests/test_join.py
tests/test_merge.py
tests/test_mesh.py
tests/test_neighbors.py
tests/test_prequantize.py
tests/test_quantize.py
tests/test_topo2geo.py
tests/test_topology.py
tests/test_topoquantize.py
tests/test_transform.py
tests/test_untransform.py
tests/hash/__init__.py
tests/hash/test_hashmap.py
tests/hash/test_hashset.py
pytopojson-1.1.2.dist-info/LICENSE
pytopojson-1.1.2.dist-info/METADATA
pytopojson-1.1.2.dist-info/WHEEL
pytopojson-1.1.2.dist-info/entry_points.txt
pytopojson-1.1.2.dist-info/top_level.txt
pytopojson-1.1.2.dist-info/RECORD
