Metadata-Version: 2.1
Name: pytopojson
Version: 1.1.2
Summary: An extension to GeoJSON that encodes topology
Home-page: https://github.com/fferrin/pytopojson
Author: Facundo Ferrín
Author-email: facundo.ferrin@gmail.com
License: UNKNOWN
Platform: UNKNOWN
Classifier: Programming Language :: Python :: 3.7
Classifier: License :: OSI Approved :: MIT License
Classifier: Operating System :: OS Independent
Requires-Python: >=3.7.3
Requires-Dist: numpy (>=1.15.0)
